.gitignore
README.rst
dev-ideas.txt
requirements.txt
setup.py
tox.ini
bin/jules
docs/Makefile
docs/api.rst
docs/conf.py
docs/getting-started.rst
docs/index.rst
docs/make.bat
docs/roadmap.rst
docs/template.rst
jules/__init__.py
jules/filters.py
jules/utils.py
jules.egg-info/PKG-INFO
jules.egg-info/SOURCES.txt
jules.egg-info/dependency_links.txt
jules.egg-info/requires.txt
jules.egg-info/top_level.txt
jules/packs/atom/atom.j2
jules/packs/atom/atom.yaml
jules/packs/atom/images/feed_icon.png
jules/packs/atom/images/feed_icon_small.png
jules/packs/bootstrap/css/bootstrap-responsive.css
jules/packs/bootstrap/css/bootstrap-responsive.min.css
jules/packs/bootstrap/css/bootstrap.css
jules/packs/bootstrap/css/bootstrap.min.css
jules/packs/bootstrap/img/glyphicons-halflings-white.png
jules/packs/bootstrap/img/glyphicons-halflings.png
jules/packs/bootstrap/js/bootstrap.js
jules/packs/bootstrap/js/bootstrap.min.js
jules/packs/foundation-icons-general-enclosed/css/foundation-icons-general-enclosed.css
jules/packs/foundation-icons-general-enclosed/fonts/foundation-icons-general-enclosed.eot
jules/packs/foundation-icons-general-enclosed/fonts/foundation-icons-general-enclosed.svg
jules/packs/foundation-icons-general-enclosed/fonts/foundation-icons-general-enclosed.ttf
jules/packs/foundation-icons-general-enclosed/fonts/foundation-icons-general-enclosed.woff
jules/packs/foundation-icons-general/css/foundation-icons-general.css
jules/packs/foundation-icons-general/fonts/foundation-icons-general.eot
jules/packs/foundation-icons-general/fonts/foundation-icons-general.otf
jules/packs/foundation-icons-general/fonts/foundation-icons-general.svg
jules/packs/foundation-icons-general/fonts/foundation-icons-general.ttf
jules/packs/foundation-icons-general/fonts/foundation-icons-general.woff
jules/packs/html5boilerplate/404.html
jules/packs/html5boilerplate/apple-touch-icon-114x114-precomposed.png
jules/packs/html5boilerplate/apple-touch-icon-57x57-precomposed.png
jules/packs/html5boilerplate/apple-touch-icon-72x72-precomposed.png
jules/packs/html5boilerplate/apple-touch-icon-precomposed.png
