Metadata-Version: 1.1
Name: jules
Version: 0.2.0.1
Summary: Yet Another Static Blog Generator I guess
Home-page: UNKNOWN
Author: Calvin Spealman
Author-email: ironfroggy@gmail.com
License: UNKNOWN
Platform: UNKNOWN
Classifier: Programming Language :: Python :: 2
Classifier: Programming Language :: Python :: 3
Classifier: Environment :: Plugins
